README.md
setup.py
esdk/__init__.py
esdk/test.py
esdk.egg-info/PKG-INFO
esdk.egg-info/SOURCES.txt
esdk.egg-info/dependency_links.txt
esdk.egg-info/requires.txt
esdk.egg-info/top_level.txt
esdk/commercial/__init__.py
esdk/commercial/ecrm/__init__.py
esdk/commercial/ecrm/api_constants.py
esdk/commercial/ecrm/api_credentials.py
esdk/commercial/ecrm/api_operations.py
esdk/commercial/ecrm/service_to_pay.py
esdk/commercial/ecrm/service_to_validate.py
esdk/payment/__init__.py
esdk/payment/en_zona/__init__.py
esdk/payment/en_zona/api_constants.py
esdk/payment/en_zona/api_credentials.py
esdk/payment/en_zona/api_payment.py
esdk/payment/transfer_movil/__init__.py
esdk/payment/transfer_movil/api_constants.py
esdk/payment/transfer_movil/api_credentials.py
esdk/payment/transfer_movil/api_payload.py
esdk/payment/transfer_movil/api_payment.py
esdk/util/__init__.py
esdk/util/api_device/__init__.py
esdk/util/api_device/api_device.py