Metadata-Version: 2.1
Name: esdk
Version: 0.0.5
Summary: Etecsa sdk
Home-page: https://github.com/sebastiancuba/esdk
Author: Sebastian Ricardo Rodriguez Mendez
Author-email: sebastian.rodriguez@etecsa.cu
License: GPL 3.0
Platform: UNKNOWN
Classifier: Programming Language :: Python :: 3
Classifier: License :: OSI Approved :: GNU General Public License v3 or later (GPLv3+)
Requires-Python: >=3.4
